indolaw_scraper/__init__.py
indolaw_scraper/cli.py
indolaw_scraper/config.py
indolaw_scraper/utils.py
indolaw_scraper/models/__init__.py
indolaw_scraper/models/document.py
indolaw_scraper/scraper/__init__.py
indolaw_scraper/scraper/bpk.py
indolaw_scraper/scraper/itb.py
indolaw_scraper/scraper/kehutanan.py
indolaw_scraper/scraper/kemendag.py
indolaw_scraper/scraper/kemendikdasmen.py
indolaw_scraper/scraper/kemenkeu.py
indolaw_scraper/scraper/kemenpora.py
indolaw_scraper/scraper/kementan.py
indolaw_scraper/scraper/kkp.py
indolaw_scraper/scraper/kominfo.py
indolaw_scraper/scraper/kpu.py
indolaw_scraper/scraper/mahkamah_agung.py
indolaw_scraper/scraper/marves.py
indolaw_scraper/scraper/pu.py
indolaw_scraper-0.1.2.dist-info/METADATA
indolaw_scraper-0.1.2.dist-info/WHEEL
indolaw_scraper-0.1.2.dist-info/top_level.txt
indolaw_scraper-0.1.2.dist-info/RECORD
